{
  "EDITOR_STATE": {
    "allProjectFiles": {
      "5aeb142c-4666-4893-a73b-9cdb87b7e846": {
        "id": "5aeb142c-4666-4893-a73b-9cdb87b7e846",
        "parent": null,
        "name": "Test350",
        "type": "DIRECTORY",
        "isDirectory": true,
        "children": [
          "cfa2bdd6-4df2-49ef-baf6-15d6c703f8dd"
        ],
        "isRemovable": false,
        "filePath": "Test350"
      },
      "cfa2bdd6-4df2-49ef-baf6-15d6c703f8dd": {
        "id": "cfa2bdd6-4df2-49ef-baf6-15d6c703f8dd",
        "parent": "5aeb142c-4666-4893-a73b-9cdb87b7e846",
        "name": "lambda.js",
        "type": "JS_LAMBDA",
        "isDirectory": false,
        "children": [],
        "isRemovable": true,
        "filePath": "Test350/lambda.js",
        "code": "exports.handler = function(event, context, callback) {\n    \n    callback(null, {\"message\": \"Successfully executed\"});\n}",
        "config": {
          "runtime": "nodejs8.10",
          "handler": "handler",
          "timeout": 60,
          "memory": 128,
          "layers": []
        },
        "triggers": [
          {
            "resourceName": "apigusEast1TestAPItestany",
            "config": {}
          }
        ]
      }
    },
    "deletedFiles": [],
    "rootNode": "5aeb142c-4666-4893-a73b-9cdb87b7e846",
    "openFiles": [
      "cfa2bdd6-4df2-49ef-baf6-15d6c703f8dd"
    ],
    "currentFileId": "cfa2bdd6-4df2-49ef-baf6-15d6c703f8dd",
    "resources": {
      "apigusEast1TestAPItestany": {
        "name": "apigusEast1TestAPItestany",
        "type": "API_GATEWAY",
        "config": {
          "selectedRegion": "us-east-1",
          "apiMode": 1,
          "apiName": "TestAPI",
          "apiId": "0itznun7w3",
          "endpointType": "EDGE",
          "rootResourceId": "h2lelj6j7k",
          "existingResources": {
            "/hiru/test": "2b8zt0",
            "/hiru": "3nc52b",
            "/hiru/sample": "4226gg",
            "/MyLambda": "98nqbj",
            "/": "h2lelj6j7k",
            "/testtwospeciallambda": "q4szm3",
            "/testtwospecialkumutest": "wey3lk",
            "/hiru/snscheck": "wok1ku"
          },
          "resourceMode": 0,
          "resourceName": "test/",
          "resourcePath": "/test/",
          "restMethod": "ANY",
          "proxyIntegration": false,
          "enableCORS": false,
          "stageMode": 0,
          "stageName": "wdw",
          "mode": 1
        }
      }
    },
    "customTemplate": {
      "dialect": null,
      "definitions": {}
    },
    "envVariables": [
      {
        "lambdaId": "all",
        "varKey": "SIGMA_AWS_ACC_ID",
        "varValue": null,
        "shouldPersist": false,
        "displayOnly": false,
        "editable": false
      }
    ],
    "packageJSON": {
      "dependencies": {}
    }
  },
  "PROJECT_META": {
    "projectName": "Test350",
    "projectDescription": "",
    "projectVersion": "1.0.0",
    "projectRegion": "us-east-1",
    "platform": "AWS",
    "platformRegions": {},
    "lastSave": 1562307251865
  },
  "VCS_STATE": {
    "provider": "GitHub",
    "repo": {
      "name": "Test350",
      "url": "https://github.com/zgma-test/Test350"
    }
  }
}